<?xml version="1.0" encoding="utf-8" ?><dwsync><file name="index.html" server="ftp.aaronstrickland.co.uk" local="3485712971" remote="602446763923846012" Dst="-1" /><file name=".DS_Store" server="ftp.aaronstrickland.co.uk" local="3485511487" remote="602446763923661932" Dst="-1" /><file name="services.html" server="ftp.aaronstrickland.co.uk" local="3485684477" remote="-4611698693685164056" Dst="-1" /><file name="about.html" server="ftp.aaronstrickland.co.uk" local="3485684136" remote="-4611698693685163996" Dst="-1" /><file name="contact.html" server="ftp.aaronstrickland.co.uk" local="3485712723" remote="7780676356" Dst="-1" /><file name="send.php" server="ftp.aaronstrickland.co.uk" local="3483967781" remote="7778931436" Dst="-1" /><file name="customdesign.html" server="ftp.aaronstrickland.co.uk" local="3485684630" remote="7780648936" Dst="-1" /><file name="emergency.html" server="ftp.aaronstrickland.co.uk" local="3485684632" remote="-4611698693685164056" Dst="-1" /><file name="gassafety.html" server="ftp.aaronstrickland.co.uk" local="3485684633" remote="-4611698693685164056" Dst="-1" /><file name="plumbingandheating.html" server="ftp.aaronstrickland.co.uk" local="3485684634" remote="-4611698693685164056" Dst="-1" /><file name="renewableenergy.html" server="ftp.aaronstrickland.co.uk" local="3485684635" remote="-4611698693685164056" Dst="-1" /><file name="contactform.php" server="ftp.aaronstrickland.co.uk" local="3484494719" remote="602446763922627952" Dst="-1" /><file name="callback.php" server="ftp.aaronstrickland.co.uk" local="3484826782" remote="1656164337992542348" Dst="-1" /><file name="process_email.php" server="ftp.aaronstrickland.co.uk" local="3484383840" remote="7779351136" Dst="-1" /><file name="quickcontact.php" server="ftp.aaronstrickland.co.uk" local="3484639620" remote="7779606916" Dst="-1" /></dwsync>